powershell_kernel/__init__.py
powershell_kernel/__main__.py
powershell_kernel/install.py
powershell_kernel/kernel.py
powershell_kernel/powershell_proxy.py
powershell_kernel/subprocess_repl.py
powershell_kernel/util.py
powershell_kernel-0.1.3.dist-info/LICENSE
powershell_kernel-0.1.3.dist-info/METADATA
powershell_kernel-0.1.3.dist-info/WHEEL
powershell_kernel-0.1.3.dist-info/top_level.txt
powershell_kernel-0.1.3.dist-info/RECORD
