Metadata-Version: 2.1
Name: powershell-kernel
Version: 0.1.3
Summary: PowerShell language kernel for Jupyter
Home-page: https://github.com/vors/jupyter-powershell
Author: Sergei Vorobev
Author-email: xvorsx@gmail.com
License: UNKNOWN
Download-URL: https://github.com/vors/jupyter-powershell/archive/0.1.3.tar.gz
Keywords: ikernel,jupyter,powershell,pwsh
Platform: UNKNOWN
